p4_stack/__init__.py
p4_stack/commands/__init__.py
p4_stack/commands/create.py
p4_stack/commands/list.py
p4_stack/commands/update.py
p4_stack/core/__init__.py
p4_stack/core/graph.py
p4_stack/core/p4_actions.py
p4_stack/core/rebase.py
p4_stack/core/types.py
p4_stack/logging_config.py
p4_stack/main.py
p4_stack-0.1.1.dist-info/LICENSE
p4_stack-0.1.1.dist-info/METADATA
p4_stack-0.1.1.dist-info/WHEEL
p4_stack-0.1.1.dist-info/entry_points.txt
p4_stack-0.1.1.dist-info/RECORD
