Metadata-Version: 2.3
Name: p4-stack
Version: 0.1.1
Summary: A CLI for stacked diffs in Perforce, bringing a Git-like workflow to P4.
License: MIT
Author: Khoa Ngo
Author-email: ngominhkhoa2006@gmail.com
Requires-Python: >=3.10
Classifier: License :: OSI Approved :: MIT License
Classifier: Programming Language :: Python :: 3
Classifier: Programming Language :: Python :: 3.10
Classifier: Programming Language :: Python :: 3.11
Classifier: Programming Language :: Python :: 3.12
Classifier: Programming Language :: Python :: 3.13
Requires-Dist: p4python (>=2025.1.2767466,<2026.0.0)
Requires-Dist: typer (>=0.20.0,<0.21.0)
